data_designer_lambda_column/__init__.py
data_designer_lambda_column/plugin.py
data_designer_lambda_column/py.typed
data_designer_lambda_column-0.1.1.dist-info/METADATA
data_designer_lambda_column-0.1.1.dist-info/WHEEL
data_designer_lambda_column-0.1.1.dist-info/entry_points.txt
data_designer_lambda_column-0.1.1.dist-info/RECORD
