Metadata-Version: 2.4
Name: data-designer-lambda-column
Version: 0.1.1
Summary: A data-designer plugin for creating columns via custom Python functions
Author-email: jmarcos <jmarcosdo@gmail.com>
Requires-Python: >=3.12
Requires-Dist: data-designer
Requires-Dist: pandas
